MANIFEST.in
setup.cfg
setup.py
sentimental/__init__.py
sentimental/example_extractor.py
sentimental/sentimental.py
sentimental.egg-info/PKG-INFO
sentimental.egg-info/SOURCES.txt
sentimental.egg-info/dependency_links.txt
sentimental.egg-info/entry_points.txt
sentimental.egg-info/requires.txt
sentimental.egg-info/top_level.txt
sentimental/data/.gitignore
sentimental/data/README.md
sentimental/data/sv/lexicon/README.md
sentimental/data/sv/lexicon/negative_examples.txt
sentimental/data/sv/lexicon/positive_examples.txt