Metadata-Version: 1.1
Name: sentimental
Version: 2.2.3
Summary: A sentiment analyzer
Home-page: https://github.com/ErikGartner/sentimental
Author: Erik Gärtner
Author-email: erik@gartner.io
License: UNKNOWN
Download-URL: https://github.com/ErikGartner/sentimental/archive/2.2.3.tar.gz
Keywords: sentiment analysis,sentiment,nlp
Platform: UNKNOWN
Classifier: Development Status :: 5 - Production/Stable
Classifier: Intended Audience :: Developers
Classifier: License :: OSI Approved :: Apache Software License
Classifier: Natural Language :: English
Classifier: Operating System :: Unix
Classifier: Programming Language :: Python :: 3.4
Classifier: Programming Language :: Python :: 3.5
Classifier: Operating System :: OS Independent
